LICENSE
MANIFEST.in
README.rst
setup.py
django_frontend_static.egg-info/PKG-INFO
django_frontend_static.egg-info/SOURCES.txt
django_frontend_static.egg-info/dependency_links.txt
django_frontend_static.egg-info/not-zip-safe
django_frontend_static.egg-info/top_level.txt
djfrontend/__init__.py
djfrontend/static/djfrontend/css/h5bp/4.2.0/h5bp.css
djfrontend/static/djfrontend/css/jquery/jquery.dataTables/1.9.4/jquery.dataTables.css
djfrontend/static/djfrontend/css/normalize/1.1.1/normalize.css
djfrontend/static/djfrontend/css/twbs/3.0.0/bootstrap-theme.css
djfrontend/static/djfrontend/css/twbs/3.0.0/bootstrap-theme.min.css
djfrontend/static/djfrontend/css/twbs/3.0.0/bootstrap.css
djfrontend/static/djfrontend/css/twbs/3.0.0/bootstrap.min.css
djfrontend/static/djfrontend/fonts/twbs/3.0.0/glyphicons-halflings-regular.eot
djfrontend/static/djfrontend/fonts/twbs/3.0.0/glyphicons-halflings-regular.svg
djfrontend/static/djfrontend/fonts/twbs/3.0.0/glyphicons-halflings-regular.ttf
djfrontend/static/djfrontend/fonts/twbs/3.0.0/glyphicons-halflings-regular.woff
djfrontend/static/djfrontend/img/famfamfam/silk/1.3/accept.png
djfrontend/static/djfrontend/img/famfamfam/silk/1.3/add.png
djfrontend/static/djfrontend/img/famfamfam/silk/1.3/anchor.png
djfrontend/static/djfrontend/img/famfamfam/silk/1.3/application.png
djfrontend/static/djfrontend/img/famfamfam/silk/1.3/application_add.png
djfrontend/static/djfrontend/img/famfamfam/silk/1.3/application_cascade.png
djfrontend/static/djfrontend/img/famfamfam/silk/1.3/application_delete.png
djfrontend/static/djfrontend/img/famfamfam/silk/1.3/application_double.png
djfrontend/static/djfrontend/img/famfamfam/silk/1.3/application_edit.png
djfrontend/static/djfrontend/img/famfamfam/silk/1.3/application_error.png
djfrontend/static/djfrontend/img/famfamfam/silk/1.3/application_form.png
djfrontend/static/djfrontend/img/famfamfam/silk/1.3/application_form_add.png
djfrontend/static/djfrontend/img/famfamfam/silk/1.3/application_form_delete.png
djfrontend/static/djfrontend/img/famfamfam/silk/1.3/application_form_edit.png
djfrontend/static/djfrontend/img/famfamfam/silk/1.3/application_form_magnify.png
djfrontend/static/djfrontend/img/famfamfam/silk/1.3/application_get.png
