Metadata-Version: 1.0
Name: django-frontend-static
Version: 1.2.0
Summary: A basic Django application to install often used static files.
Home-page: http://github.com/jonfaustman/django-frontend-static
Author: Jon Faustman
Author-email: jon@faustman.org
License: MIT
Platform: UNKNOWN
Classifier: Development Status :: 7 - Inactive
Classifier: Environment :: Web Environment
Classifier: Intended Audience :: End Users/Desktop
Classifier: Natural Language :: English
Classifier: Operating System :: OS Independent
Classifier: Framework :: Django
Classifier: Programming Language :: Python
Classifier: Topic :: Internet :: WWW/HTTP :: Dynamic Content :: CGI Tools/Libraries
Classifier: Topic :: Utilities
Classifier: License :: OSI Approved :: MIT License
